Workbook

Sheet Form blank
A1: PHIẾU YÊU CẦU BÁO GIÁ HÀNG GIÁN TIẾP
A2: Indirect Goods Quotation Request Form
B4: Ngày/tháng Date/month(*) | H4: Số đơn yêu cầu báo giá Quotation Request Number
A6: Dòng chảy form: PIC phòng ban có yêu cầu > Quản lý sơ cấp > Quản lý trung cấp > PIC Pur > Quản lý sơ cấp Pur フォーム流れ: 要求課PIC > 要求課初級管理職 > 要求課中級管理職 > Pur課PIC > Pur課係長
A7: 1 | B7: 2 | C7: 3 | D7: 4 | E7: 5 | F7: 6 | G7: 7 | H7: 8 | I7: 9 | J7: 10 | K7: 11 | L7: 12 | M7: =L7+1 -> 13 | S7: 14 | T7: =S7+1 -> 15 | U7: =T7+1 -> 16 | V7: =U7+1 -> 17 | W7: =V7+1 -> 18 | X7: =W7+1 -> 19 | Y7: =X7+1 -> 20 | Z7: =Y7+1 -> 21 | AA7: =Z7+1 -> 22 | ... AF7: =AE7+1 -> 27
A8: No | B8: Request section code(*) mã phòng ban | C8: Section (*) Tên phòng | D8: Phân loại Category (A/E/non list) | E8: Mã thiết bị Equipment code | F8: Mã hàng nội bộ BIVN's part code | G8: Mã hàng của NCC Vendor's good code | H8: Tên hàng VN dùng để mở thủ tục hải quan (dự thảo)(*) Part name (Vietnamese) | I8: Tên hàng tiếng anh(*) Part name (English) | J8: Số lượng Quanlity(*) | K8: Đơn vị Unit(*) | L8: Chủng loại hàng Part category | M8: Mô tả hàng hóa Description of goods | S8: Yêu cầu ROHS ROHS requirements | T8: Yêu cầu CO/CQ CO/Cqrequirements | U8: Yêu cầu MSDS kèm số CAS (đối với hóa chất) Request MSDS with CAS number (for chemicals) | V8: Yêu cầu tiêu chuẩn an toàn Request for safety standards | W8: File Thiết kế Design(*) | X8: Nhà Sản xuất Maker | Y8: Mã nhà cung cấp Vendor code | Z8: Tên nhà cung cấp Vendor name | AA8: Lấy báo giá? Is it a quotation request(*) | AB8: Lý do không lấy báo giá Reason for not making a request | AC8: Ngày muốn nhận hàng Desired delivery date(*) | AD8: Kỳ hạn lựa chọn NCC Deadline for deciding vendor(*) | AE8: GẤP urgent | AF8: Người yêu cầu Request person in charge
M9: Hình dáng Shape | N9: Chất liệu Material | O9: Thành phần, hàm lượng (đối với hóa chất) Composition, Content (for Chemicals) | P9: Kích thước(mm) (dài/rộng/cao) Dimensions (mm) (Length/Width/Height) | Q9: Dùng cho máy/thiết bị/vị trí nào Which machine/equipment/location is it used for | R9: Dùng đề làm gì (tính năng) Purpose of use (or function)
A10: 1 | B10: 2210 | C10: =VLOOKUP(B10,Master!A:B,2,0) -> PR2-PR2 COMMON | D10: E | F10: E000299 | H10: =M10&" "&N10&" "&O10&""&P10&" "&Q10&" "&R10 | AA10: X | AC10: 46142 | AD10: 46082 | AE10: O | AF10: Lan 1
A11: 2 | B11: 2210 | C11: =VLOOKUP(B11,Master!A:B,2,0) -> PR2-PR2 COMMON | D11: A | F11: A000018 | H11: =M11&" "&N11&" "&O11&""&P11&" "&Q11&" "&R11 | AA11: O | AC11: 46142 | AD11: 46082 | AF11: Lan 2
A12: 3 | B12: 2210 | C12: =VLOOKUP(B12,Master!A:B,2,0) -> PR2-PR2 COMMON | D12: E | F12: E000300 | H12: =M12&" "&N12&" "&O12&""&P12&" "&Q12&" "&R12 | AA12: O | AC12: 46142 | AD12: 46082 | AF12: Lan 3
A13: 4 | B13: 2210 | C13: =VLOOKUP(B13,Master!A:B,2,0) -> PR2-PR2 COMMON | D13: A | F13: A000014 | H13: =M13&" "&N13&" "&O13&""&P13&" "&Q13&" "&R13 | AA13: O | AC13: 46142 | AD13: 46082 | AF13: Lan 4
A14: 5 | B14: 2210 | C14: =VLOOKUP(B14,Master!A:B,2,0) -> PR2-PR2 COMMON | G14: XYZ1 | H14: =M14&" "&N14&" "&O14&""&P14&" "&Q14&" "&R14 -> A1 A2 A3A4 A5 A6 | L14: Đầu cốt | M14: A1 | N14: A2 | O14: A3 | P14: A4 | Q14: A5 | R14: A6 | S14: Need (cần) | T14: CQ | W14: \\apbivnap12\Share\Project_Document\Cost management\01_Clearifycation\2025-PUR-PUR_Quoctaion_Request\Link test bản vẽ đính kèm.xlsx | AA14: O | AC14: 46142 | AD14: 46082 | AE14: O | AF14: Lan 5
A15: 6 | B15: 2210 | C15: =VLOOKUP(B15,Master!A:B,2,0) -> PR2-PR2 COMMON | G15: XYZ2 | H15: =M15&" "&N15&" "&O15&""&P15&" "&Q15&" "&R15 -> B1 B2 B3B4 B5 B6 | L15: Thước cặp | M15: B1 | N15: B2 | O15: B3 | P15: B4 | Q15: B5 | R15: B6 | W15: \\apbivnap12\Share\Project_Document\Cost management\01_Clearifycation\2025-PUR-PUR_Quoctaion_Request\Link test bản vẽ đính kèm.xlsx | AA15: O | AC15: 46142 | AD15: 46082 | AF15: Lan 6
A16: 7 | B16: 2210 | C16: =VLOOKUP(B16,Master!A:B,2,0) -> PR2-PR2 COMMON | G16: XYZ3 | H16: =M16&" "&N16&" "&O16&""&P16&" "&Q16&" "&R16 -> C1 C2 C3C4 C5 C6 | L16: Mặt bàn xanh | M16: C1 | N16: C2 | O16: C3 | P16: C4 | Q16: C5 | R16: C6 | W16: \\apbivnap12\Share\Project_Document\Cost management\01_Clearifycation\2025-PUR-PUR_Quoctaion_Request\Link test bản vẽ đính kèm.xlsx | AA16: O | AC16: 46142 | AD16: 46082 | AF16: Lan 7
A17: 8 | B17: 2210 | C17: =VLOOKUP(B17,Master!A:B,2,0) -> PR2-PR2 COMMON | G17: XYZ4 | H17: =M17&" "&N17&" "&O17&""&P17&" "&Q17&" "&R17 -> D1 D2 D3D4 D5 D6 | L17: Thùng danpla | M17: D1 | N17: D2 | O17: D3 | P17: D4 | Q17: D5 | R17: D6 | W17: \\apbivnap12\Share\Project_Document\Cost management\01_Clearifycation\2025-PUR-PUR_Quoctaion_Request\Link test bản vẽ đính kèm.xlsx | AA17: O | AC17: 46142 | AD17: 46082 | AF17: Lan 8
A18: 9 | B18: 2210 | C18: =VLOOKUP(B18,Master!A:B,2,0) -> PR2-PR2 COMMON | G18: XYZ5 | H18: =M18&" "&N18&" "&O18&""&P18&" "&Q18&" "&R18 -> E1 E2 E3E4 E5 E6 | L18: Cáp kết nối thước cặp tới U-wave-T | M18: E1 | N18: E2 | O18: E3 | P18: E4 | Q18: E5 | R18: E6 | W18: \\apbivnap12\Share\Project_Document\Cost management\01_Clearifycation\2025-PUR-PUR_Quoctaion_Request\Link test bản vẽ đính kèm.xlsx | AA18: O | AC18: 46142 | AD18: 46082 | AF18: Lan 9
A19: 10 | B19: 2210 | C19: =VLOOKUP(B19,Master!A:B,2,0) -> PR2-PR2 COMMON | G19: XYZ6 | H19: =M19&" "&N19&" "&O19&""&P19&" "&Q19&" "&R19 -> F1 F2 F3F4 F5 F6 | L19: Bánh xe | M19: F1 | N19: F2 | O19: F3 | P19: F4 | Q19: F5 | R19: F6 | S19: Need (cần) | W19: \\apbivnap12\Share\Project_Document\Cost management\01_Clearifycation\2025-PUR-PUR_Quoctaion_Request\Link test bản vẽ đính kèm.xlsx | X19: Hammer | AA19: O | AC19: 46142 | AD19: 46082 | AF19: Lan 10
A20: 11 | B20: 2210 | C20: =VLOOKUP(B20,Master!A:B,2,0) -> PR2-PR2 COMMON | G20: XYZ7 | H20: =M20&" "&N20&" "&O20&""&P20&" "&Q20&" "&R20 -> G1 G2 G3G4 G5 G6 | L20: Giấy (văn phòng) Paper (Office) | M20: G1 | N20: G2 | O20: G3 | P20: G4 | Q20: G5 | R20: G6 | S20: Need (cần) | W20: \\apbivnap12\Share\Project_Document\Cost management\01_Clearifycation\2025-PUR-PUR_Quoctaion_Request\Link test bản vẽ đính kèm.xlsx | AA20: O | AC20: 46142 | AD20: 46082 | AE20: O | AF20: Lan 11
A21: 12 | C21: =VLOOKUP(B21,Master!A:B,2,0) -> #N/A | G21: XYZ8 | H21: =M21&" "&N21&" "&O21&""&P21&" "&Q21&" "&R21 -> K1 K2 K3K4 K5 K6 | L21: Bánh xe | M21: K1 | N21: K2 | O21: K3 | P21: K4 | Q21: K5 | R21: K6 | W21: \\apbivnap12\Share\Project_Document\Cost management\01_Clearifycation\2025-PUR-PUR_Quoctaion_Request\Link test bản vẽ đính kèm.xlsx | X21: Spacio | AA21: O | AC21: 46142 | AD21: 46082 | AF21: Lan 12
A22: 13 | C22: =VLOOKUP(B22,Master!A:B,2,0) -> #N/A | H22: =M22&" "&N22&" "&O22&""&P22&" "&Q22&" "&R22 | AA22: O
A23: 14 | C23: =VLOOKUP(B23,Master!A:B,2,0) -> #N/A | H23: =M23&" "&N23&" "&O23&""&P23&" "&Q23&" "&R23 | AA23: O
A24: 15 | C24: =VLOOKUP(B24,Master!A:B,2,0) -> #N/A | H24: =M24&" "&N24&" "&O24&""&P24&" "&Q24&" "&R24 | AA24: O
A25: 16 | C25: =VLOOKUP(B25,Master!A:B,2,0) -> #N/A | H25: =M25&" "&N25&" "&O25&""&P25&" "&Q25&" "&R25 | AA25: O
A26: 17 | C26: =VLOOKUP(B26,Master!A:B,2,0) -> #N/A | H26: =M26&" "&N26&" "&O26&""&P26&" "&Q26&" "&R26 | AA26: O
A27: 18 | C27: =VLOOKUP(B27,Master!A:B,2,0) -> #N/A | H27: =M27&" "&N27&" "&O27&""&P27&" "&Q27&" "&R27 | AA27: O
A28: 19 | C28: =VLOOKUP(B28,Master!A:B,2,0) -> #N/A | H28: =M28&" "&N28&" "&O28&""&P28&" "&Q28&" "&R28 | AA28: O
A29: 20 | C29: =VLOOKUP(B29,Master!A:B,2,0) -> #N/A | H29: =M29&" "&N29&" "&O29&""&P29&" "&Q29&" "&R29 | AA29: O

Sheet フォーム説明
E1: Hàng cũ đang/đã sử dụng 注文した部品 | F1: Hàng mới (chưa nhập về BIVN bao giờ) 新設部品
B2: Ngày 日付(*) | E2: Hàm tự động公式 | F2: Hàm tự động公式
B3: Số đơn | E3: Hàm tự động公式 | F3: Hàm tự động公式 | G3: RQ-nămthángngay-Số thứ tự đơn trong ngày
B4: 1 | C4: No | E4: Bắt buộc điền 必要 | F4: Bắt buộc điền 必要
B5: 2 | C5: Request section code(*) mã phòng ban | E5: Bắt buộc điền 必要 | F5: Bắt buộc điền 必要
B6: 3 | C6: Section (*) Tên phòng | E6: Hàm tự động公式 | F6: Hàm tự động公式 | G6: Link theo mã phòng 部署コードによるリンク
B7: 4 | C7: Phân loại Category (A/E/non list) | E7: Hàm tự động公式 | F7: Bắt buộc điền 必要 | G7: Mã cũ: Link theo master Mã mới: Chọn A,E,Ngoài danh mục 旧コード：マスターによるリンク 新コード：A、E、カテゴリ外を選択
B8: 5 | C8: Mã thiết bị Equipment code | E8: Không bắt buộc （不要） | F8: Không bắt buộc （不要） | G8: Phòng nào cần quản lý theo 1 thiết bị hoặc 1 khuôn (như RD PE hoặc MPE) thì điền mã thiết bị hoặc mã khuôn vào cột này. Mục đích sau này hệ thống sẽ phát triển là có thể check được giá cho cả thiết bị khi lấy đủ báo giá các mặt hàng nhỏ dùng lắp lên nó RD PEやMPEのように、1つの設備または1つの金型で管理する必要がある部門は、この列に設備コードまたは金型コードを入力してください。 将来的には、システムを拡張し、関連する小部品の見積もりが揃った際に、設備全体の価格を確認できるようにすることを目的としています。
B9: 6 | C9: Mã hàng nội bộ BIVN's part code | E9: Bắt buộc điền 必要 | F9: Không bắt buộc （不要） | G9: Hiện tại có mã nội bộ cho hàng A và E Sau đây thì cả hàng ngoài danh mục cũng sẽ thực hiện tạo mã nội bộ 現在、A品とE品には社内コードがあります。 今後は、リスト外の商品についても社内コードを作成します。
B10: 7 | C10: Mã hàng của NCC Vendor's good code | E10: Hàm tự động公式 | F10: Bắt buộc điền 必要 | G10: Với hàng thị trường bán đại trà : chính là mã/đời model hàng hóa mà NCC đăng trong danh mục hàng hóa trên Web Với hàng tự thiết kế (BIVN/hay NCC): dùng code bản vẽ 市場で一般販売されている商品については、サプライヤーがWeb上の商品リストに掲載している商品コード／モデル番号を使用します。 自社設計品（BIVNまたはサプライヤー）の場合は、図面コードを使用します。
B11: 8 | C11: Tên hàng VN dùng để mở thủ tục hải quan (dự thảo)(*) Part name (Vietnamese) | E11: Hàm tự động公式 | F11: Bắt buộc điền 必要 | G11: Mã đã mua: Vlook up theo master Mã mới: Ghi tên tiếng Việt tự đặt dựa vào phần mô tả hàng hóa 旧コード：マスターに基づくVlook up 新コード：商品の説明に基づいて自分で設定したベトナム語名を記入 Cột này chỉ là tên dự thảo của phòng ban, sau Ship sẽ xác nhận lại trước khi phát hành đơn yêu cầu hàng hóa 商品の説明部分の関数＆。通関手続きの名称は使用目的によって変更されます。 この列は部門による仮の名称であり、出荷後に購買依頼書を発行する前に確認されます。
B12: 9 | C12: Tên hàng tiếng anh(*) Part name (English) | E12: Hàm tự động公式 | F12: Bắt buộc điền 必要
B13: 10 | C13: Số lượng Quanlity(*) | E13: Bắt buộc điền 必要 | F13: Bắt buộc điền 必要
B14: 11 | C14: Đơn vị Unit(*) | E14: Bắt buộc điền 必要 | F14: Bắt buộc điền 必要
B15: 12 | C15: Chủng loại hàng Part category | E15: Hàm tự động公式 | F15: Bắt buộc điền 必要 | G15: Mã mới: Lựa chọn trong chủng loại hàng hóa trong master, nếu phát sinh chủng loại mới cần phải liên lạc Pur tạo master thì mới có thể lựa chọn 新コード：マスター内の品目カテゴリから選択、新しいカテゴリが発生した場合は、選択する前にPurに連絡してマスターを作成する必要があります。
B16: =B15+1 -> 13 | C16: Mô tả hàng hóa Description of goods | D16: Hình dáng Shape | E16: Hàm tự động公式 | F16: Bắt buộc điền 必要 | G16: Ví dụ : tấm, khay , hộp, giá đỡ, tên thiết bị, tên dụng cụ... Chú ý: Có thể gắn thêm ảnh mô tả nhưng vẫn phải mô tả bằng ngôn ngữ Mã đã mua: Link luôn tên hàng dùng để mở hải quan cũ 例: プレート、トレー、ボックス、ホルダー、機器名、ツール名など 注意: 説明文に言語を使用する必要があるが、説明用の画像を追加することも可能 購入済みコード：旧税関を開けるために使用した商品の名前をリンクする
D17: Chất liệu Material | E17: Không bắt buộc （不要） | F17: Bắt buộc điền 必要 | G17: Ví dụ: inox, nhựa... Nếu có nhiều loại NVL thì ghi 1 vài NVL chính cấu thành (chiếm tầm 80~90%) Mã đã mua: Để trống 例: ステンレス、プラスチックなど 複数の材料がある場合は、主な構成材料（全体の約80〜90％を占めるもの）をいくつか記載してください。 購入済みコード：空欄のままにする
D18: Thành phần, hàm lượng (đối với hóa chất) Composition, Content (for Chemicals) | E18: Không bắt buộc （不要） | F18: Bắt buộc điền 必要 | G18: nếu chưa có MSDS thì tra trên mạng và ghi thành phần chính (sao cho chiếm 90% tổng số Mã đã mua: Để trống MSDSがない場合は、インターネットで調べて主な成分（全体の90%を占めるもの）を記載してください。 旧コード：空欄のままにする
D19: Kích thước(mm) (dài/rộng/cao) Dimensions (mm) (Length/Width/Height) | E19: Không bắt buộc （不要） | F19: Bắt buộc điền 必要 | G19: Viết đúng theo thứ tự quy định , đơn vị mm Mã đã mua: Để trống 規定された順序に従って正しく記入し、単位はmmで記載してください。 旧コード：空欄のままにする
D20: Dùng cho máy/thiết bị/vị trí nào Which machine/equipment/location is it used for | E20: Tùy đối tượng | F20: Bắt buộc điền 必要 | G20: ví dụ: máy A, vị trí thao tác lắp cụm frame.... Mã đã mua: Nếu không thay đổi thì copy sang 例: A機械、フレームユニットを取り付ける作業位置... 旧コード：変更がない場合はコピーしてください
D21: Dùng đề làm gì (tính năng) Purpose of use (or function) | E21: Tùy đối tượng | F21: Bắt buộc điền 必要 | G21: 例: 携帯電話からパソコンに接続する、通路と射出成形機の間に障害物がある… 旧コード：変更がない場合はコピーしてください
B22: 14 | C22: Yêu cầu ROHS ROHS requirements | E22: Không bắt buộc （不要） | F22: Không bắt buộc （不要） | G22: Tuỳ yêu cầu phòng ban 部門の要求に応じて Cần điền "O", Không cần bỏ trống
B23: =B22+1 -> 15 | C23: Yêu cầu CO/CQ CO/Cqrequirements | E23: Không bắt buộc （不要） | F23: Không bắt buộc （不要） | G23: Tuỳ yêu cầu phòng ban 部門の要求に応じて Cần điền "O", Không cần bỏ trống
B24: =B23+1 -> 16 | C24: Yêu cầu MSDS kèm số CAS (đối với hóa chất) Request MSDS with CAS number (for chemicals) | E24: Không bắt buộc （不要） | F24: Không bắt buộc （不要） | G24: Tuỳ yêu cầu phòng ban 部門の要求に応じて Cần điền "O", Không cần bỏ trống
B25: =B24+1 -> 17 | C25: Yêu cầu tiêu chuẩn an toàn Request for safety standards | E25: Không bắt buộc （不要） | F25: Không bắt buộc （不要） | G25: Tuỳ yêu cầu phòng ban 部門の要求に応じて Cần điền "O", Không cần bỏ trống
B26: =B25+1 -> 18 | C26: File Thiết kế Design(*) | E26: Tùy đối tượng | F26: Bắt buộc điền 必要 | G26: 1 chủng loại linh kiện 1 link BOX kèm mật khẩu 1種類の部品につき1つのBOXリンクとパスワードを付けてください Hàng ngoài danh mục thì cũ hay mới đều bắt buộc Hàng thị trường thì không cần
B27: =B26+1 -> 19 | C27: Nhà Sản xuất Maker | E27: Hàm tự động公式 | F27: Bắt buộc điền 必要 | G27: Điền tên nhãn hãng sản xuất cho mã hàng đó その商品コードに対してメーカー名を記入してください
B28: =B27+1 -> 20 | C28: Mã nhà cung cấp Vendor code | E28: Hàm tự động公式 | F28: Hàm tự động公式 | G28: Link từ cột chủng loại hàng+master 品目カテゴリー+マスターからのリンク
B29: =B28+1 -> 21 | C29: Tên nhà cung cấp Vendor name | E29: Hàm tự động公式 | F29: Hàm tự động公式 | G29: Link từ cột chủng loại hàng+master 品目カテゴリー+マスターからのリンク
B30: =B29+1 -> 22 | C30: Lấy báo giá? Is it a quotation request(*) | E30: Bắt buộc điền 必要 | F30: Bắt buộc điền 必要 | G30: O: cần lấy báo giá X: Không cần Nếu Không muốn lấy báo gía NCC nào thì PIC tự đổi thành X dòng tương ứng tên NCC đó O: 見積りが必要 X: 必要なし 特定の仕入先から見積りを取りたくない場合は、担当者がその仕入先名に対応する行をXに変更してください
B31: =B30+1 -> 23 | C31: Lý do không lấy báo giá Reason for not making a request | E31: Bắt buộc điền 必要 | F31: Bắt buộc điền 必要 | G31: Chỉ Điền lý do hợp lý với các NCC chọn X ở cột số 22 các dòng tick "O" thì ko cần 列22で「X」を選択した仕入先には、合理的な理由のみ記入してください。 「O」をチェックした行については必要ありません。
B32: =B31+1 -> 24 | C32: Ngày muốn nhận hàng Desired delivery date(*) | E32: Bắt buộc điền 必要 | F32: Bắt buộc điền 必要
B33: =B32+1 -> 25 | C33: Kỳ hạn lựa chọn NCC Deadline for deciding vendor(*) | E33: Bắt buộc điền 必要 | F33: Bắt buộc điền 必要 | G33: Gấp : 3 ngày Thông thường : 3 ngày làm việc/10 linh kiện Chỉ tính từ khi có đủ thông tin lấy báo giá 緊急: 3日 通常: 3営業日/10部品 見積取得に必要な情報が揃ってからカウントします。
B34: =B33+1 -> 26 | C34: GẤP urgent | E34: Không bắt buộc （不要） | F34: Không bắt buộc （不要） | G34: Gấp thì tick O không thi bỏ trống 緊急の場合は「O」を入れ、それ以外は空欄にしてください。
B35: =B34+1 -> 27 | C35: Người yêu cầu Request person in charge | E35: Không bắt buộc （不要） | F35: Không bắt buộc （不要） | G35: Phòng ban nào cần quản lý thông tin người đưa yêu cầu thì điền, còn không thì bỏ trống 要求者の情報を管理する必要がある部署は記入してください。それ以外の場合は空欄にしてください。

Sheet Master
A1: Mã phòng | B1: tên phòng
A2: 1110 | B2: GA-GA-CANTEEN
A3: 1130 | B3: GA-GA-DORMITORY
A4: 1210 | B4: GA-GA
A5: 1211 | B5: ADM-PER
A6: 1212 | B6: GA-SFE
A7: 1220 | B7: GA-FAC
A8: 1221 | B8: TT Factory GA COMMON
A9: 1310 | B9: ADM-ACC
A10: 1410 | B10: ADM-MP
A11: 2210 | B11: PR2-PR2 COMMON
A12: 2310 | B12: R&D-PE
... A169: Y0294100 | B169: DOMINO-QA
B170: (blank)
A171: Grand Total

Sheet Sheet4
C2: Thẩm tra審査 | G2: Dự thảo 起案
C3: QLSC phòng Pur 購買係長 | D3: PIC phòng Pur 購買スタッフ | E3: QLTC phòng ban 中級管理職 | F3: QLSC phòng ban 要求課係長 | G3: PIC phòng ban 要求課スタッフ
